README.txt
setup.py
collective/__init__.py
collective.keywordcondition.egg-info/PKG-INFO
collective.keywordcondition.egg-info/SOURCES.txt
collective.keywordcondition.egg-info/dependency_links.txt
collective.keywordcondition.egg-info/entry_points.txt
collective.keywordcondition.egg-info/namespace_packages.txt
collective.keywordcondition.egg-info/paster_plugins.txt
collective.keywordcondition.egg-info/requires.txt
collective.keywordcondition.egg-info/top_level.txt
collective.keywordcondition.egg-info/zip-safe
collective/keywordcondition/__init__.py
collective/keywordcondition/configure.zcml
collective/keywordcondition/keyword.py
collective/keywordcondition/tests.py
docs/HISTORY.txt
docs/INSTALL.txt
docs/LICENSE.GPL
docs/LICENSE.txt
