Metadata-Version: 1.0
Name: collective.keywordcondition
Version: 1.0b1
Summary: A condition for Plone 3's content rules that checks keywords on a content item
Home-page: http://plone.org
Author: Martin Aspeli
Author-email: optilude@gmail.com
License: GPL
Keywords: Plone content rules
Platform: UNKNOWN
Classifier: Framework :: Plone
Classifier: Framework :: Zope2
Classifier: Framework :: Zope3
Classifier: Programming Language :: Python
Classifier: Topic :: Software Development :: Libraries :: Python Modules
